jsoncompact/__init__.py
jsoncompact/main.py
jsoncompact/serde.py
jsoncompact/types.py
jsoncompact-0.1.1.dist-info/licenses/LICENSE
jsoncompact-0.1.1.dist-info/WHEEL
jsoncompact-0.1.1.dist-info/METADATA
jsoncompact-0.1.1.dist-info/RECORD
