Metadata-Version: 2.4
Name: jsoncompact
Version: 0.1.1
Summary: JSON Schema serializer/deserializer
Author: Lorenzo Curcio
Author-email: Lorenzo Curcio <lorenzocurcio2@gmail.com>
License-Expression: MIT
License-File: LICENSE
Classifier: Development Status :: 3 - Alpha
Classifier: Operating System :: OS Independent
Classifier: Programming Language :: Python
Classifier: Programming Language :: Python :: 3
Classifier: Programming Language :: Python :: 3 :: Only
Requires-Dist: orjson>=3.11.5 ; extra == 'orjson'
Requires-Dist: ormsgpack>=1.12.1 ; extra == 'ormsgpack'
Requires-Python: >=3.10
Provides-Extra: orjson
Provides-Extra: ormsgpack
